mobile_sam/__init__.py
mobile_sam/automatic_mask_generator.py
mobile_sam/build_sam.py
mobile_sam/predictor.py
mobile_sam/modeling/__init__.py
mobile_sam/modeling/common.py
mobile_sam/modeling/image_encoder.py
mobile_sam/modeling/mask_decoder.py
mobile_sam/modeling/prompt_encoder.py
mobile_sam/modeling/sam.py
mobile_sam/modeling/tiny_vit_sam.py
mobile_sam/modeling/transformer.py
mobile_sam/utils/__init__.py
mobile_sam/utils/amg.py
mobile_sam/utils/onnx.py
mobile_sam/utils/transforms.py
mobilesam_mirror-1.0.0.dist-info/licenses/LICENSE
mobilesam_mirror-1.0.0.dist-info/METADATA
mobilesam_mirror-1.0.0.dist-info/WHEEL
mobilesam_mirror-1.0.0.dist-info/top_level.txt
mobilesam_mirror-1.0.0.dist-info/RECORD
