Metadata-Version: 2.4
Name: mobilesam-mirror
Version: 1.0.0
Summary: Packaging mirror of MobileSAM
Home-page: https://github.com/Artificial-Sweetener/MobileSAM-Mirror
Author: MobileSAM authors
Maintainer: Artificial Sweetener
License:                                  Apache License
Project-URL: Homepage, https://github.com/ChaoningZhang/MobileSAM
Project-URL: Mirror, https://github.com/Artificial-Sweetener/MobileSAM-Mirror
Requires-Python: >=3.8
License-File: LICENSE
Provides-Extra: all
Requires-Dist: matplotlib; extra == "all"
Requires-Dist: pycocotools; extra == "all"
Requires-Dist: opencv-python; extra == "all"
Requires-Dist: onnx; extra == "all"
Requires-Dist: onnxruntime; extra == "all"
Provides-Extra: dev
Requires-Dist: flake8; extra == "dev"
Requires-Dist: isort; extra == "dev"
Requires-Dist: black; extra == "dev"
Requires-Dist: mypy; extra == "dev"
Dynamic: home-page
Dynamic: license-file
Dynamic: requires-python
